wcpan/jav/__init__.py
wcpan/jav/__main__.py
wcpan/jav/_main.py
wcpan/jav/py.typed
wcpan/jav/types.py
wcpan/jav/_sauces/_10musume.py
wcpan/jav/_sauces/_1pondo.py
wcpan/jav/_sauces/__init__.py
wcpan/jav/_sauces/_carib.py
wcpan/jav/_sauces/_caribpr.py
wcpan/jav/_sauces/_fanza.py
wcpan/jav/_sauces/_fc2.py
wcpan/jav/_sauces/_heydouga.py
wcpan/jav/_sauces/_heyzo.py
wcpan/jav/_sauces/_javbee.py
wcpan/jav/_sauces/_lib.py
wcpan/jav/_sauces/_mgstage.py
wcpan/jav/_sauces/_tokyohot.py
wcpan/jav/_sauces/_types.py
wcpan/jav/_sauces/lib.py
wcpan_jav-0.2.4.dist-info/METADATA
wcpan_jav-0.2.4.dist-info/WHEEL
wcpan_jav-0.2.4.dist-info/licenses/LICENSE.txt
wcpan_jav-0.2.4.dist-info/RECORD
